MANIFEST.in
README.rst
setup.py
version
src/falcors/__init__.py
src/falcors/log.py
src/falcors/middleware.py
src/falcors.egg-info/PKG-INFO
src/falcors.egg-info/SOURCES.txt
src/falcors.egg-info/dependency_links.txt
src/falcors.egg-info/requires.txt
src/falcors.egg-info/top_level.txt